[{"categories":[""],"extensions":[{"categories":[""],"provides":[{"service":"org.eclipse.edc.connector.dataplane.selector.spi.client.DataPlaneSelectorClient"}],"references":[{"service":"org.eclipse.edc.connector.dataplane.selector.spi.DataPlaneSelectorService","required":false},{"service":"org.eclipse.edc.spi.http.EdcHttpClient","required":false},{"service":"org.eclipse.edc.spi.types.TypeManager","required":true}],"configuration":[{"key":"edc.dpf.selector.url","required":false,"type":"string","description":""}],"name":"DataPlane instance client","type":"extension","overview":"No overview provided.","className":"org.eclipse.edc.connector.dataplane.selector.DataPlaneInstanceClientExtension"}],"extensionPoints":[],"modulePath":"org.eclipse.edc:data-plane-selector-client","version":"0.0.1-20230220.patch1-SNAPSHOT","name":null}]